gconnect/__init__.py
gconnect/call_options.py
gconnect/client.py
gconnect/client_interceptor.py
gconnect/code.py
gconnect/codec.py
gconnect/compression.py
gconnect/connect.py
gconnect/connection_pool.py
gconnect/content_stream.py
gconnect/envelope.py
gconnect/error.py
gconnect/handler.py
gconnect/handler_context.py
gconnect/handler_interceptor.py
gconnect/headers.py
gconnect/idempotency_level.py
gconnect/middleware.py
gconnect/options.py
gconnect/protocol.py
gconnect/request.py
gconnect/response.py
gconnect/response_writer.py
gconnect/utils.py
gconnect/version.py
gconnect/asgi_helpers/__init__.py
gconnect/asgi_helpers/utils.py
gconnect/protocol_connect/__init__.py
gconnect/protocol_connect/base64_utils.py
gconnect/protocol_connect/connect_client.py
gconnect/protocol_connect/connect_handler.py
gconnect/protocol_connect/connect_protocol.py
gconnect/protocol_connect/constants.py
gconnect/protocol_connect/content_type.py
gconnect/protocol_connect/end_stream.py
gconnect/protocol_connect/error_code.py
gconnect/protocol_connect/error_json.py
gconnect/protocol_connect/marshaler.py
gconnect/protocol_connect/unmarshaler.py
gconnect/protocol_grpc/__init__.py
gconnect/protocol_grpc/constants.py
gconnect/protocol_grpc/content_type.py
gconnect/protocol_grpc/error_trailer.py
gconnect/protocol_grpc/grpc_client.py
gconnect/protocol_grpc/grpc_handler.py
gconnect/protocol_grpc/grpc_protocol.py
gconnect/protocol_grpc/marshaler.py
gconnect/protocol_grpc/unmarshaler.py
gconnect-0.0.1.dist-info/METADATA
gconnect-0.0.1.dist-info/WHEEL
gconnect-0.0.1.dist-info/licenses/LICENSE
gconnect-0.0.1.dist-info/RECORD
