Metadata-Version: 2.4
Name: gconnect
Version: 0.0.1
Summary: The Python implementation of Connect: Protobuf RPC that works.
Author-email: tsubakiky <salovers1205@gmail.com>
License: Apache-2.0
License-File: LICENSE
Requires-Python: >=3.13
Requires-Dist: anyio>=4.7.0
Requires-Dist: googleapis-common-protos>=1.70.0
Requires-Dist: h2>=4.2.0
Requires-Dist: httpcore
Requires-Dist: protobuf>=5.29.1
Requires-Dist: pydantic>=2.10.4
Requires-Dist: starlette>=0.46.0
Requires-Dist: types-protobuf>=5.29.1.20241207
Requires-Dist: yarl>=1.18.3
